LICENSE
MANIFEST.in
README.md
setup.py
datafile/t.txt
datafile/tmsample.py
src/tajk_data2.c
src/tajk_data2.h
src/tajk_lib.c
src/tajk_lib.h
src/tajk_modify.c
src/tajk_modify.h
src/tamodify.c
tamodify.egg-info/PKG-INFO
tamodify.egg-info/SOURCES.txt
tamodify.egg-info/dependency_links.txt
tamodify.egg-info/not-zip-safe
tamodify.egg-info/top_level.txt