Metadata-Version: 2.1
Name: tamodify
Version: 0.1.6
Summary: TA接口文件修改
Home-page: https://gitee.com/chenc224/ofbdep/tree/master/python
Author: Chen chuan
Author-email: 13902950907@139.com
Classifier: Programming Language :: Python :: 3
Classifier: License :: OSI Approved :: MIT License
Classifier: Operating System :: OS Independent
Requires-Python: >=3.5
License-File: LICENSE
